hotdag/__about__.py
hotdag/__init__.py
hotdag/dbt_cloud.py
hotdag/dbt_core.py
hotdag/main.py
hotdag/manifest.py
hotdag/renderer.py
hotdag/test_main.http
hotdag/server/__init__.py
hotdag/server/server.py
hotdag/server/routers/__init__.py
hotdag/server/routers/cloud.py
hotdag/server/routers/manifest.py
hotdag/server/routers/url.py
hotdag-0.7.2.dist-info/METADATA
hotdag-0.7.2.dist-info/WHEEL
hotdag-0.7.2.dist-info/entry_points.txt
hotdag-0.7.2.dist-info/licenses/LICENSE.txt
hotdag-0.7.2.dist-info/RECORD
